XStatic_JQuery.TableSorter-2.14.5.2-py3.6-nspkg.pth
xstatic/pkg/jquery_tablesorter/__init__.py
xstatic/pkg/jquery_tablesorter/data/jquery.tablesorter.js
XStatic_JQuery.TableSorter-2.14.5.2.dist-info/METADATA
XStatic_JQuery.TableSorter-2.14.5.2.dist-info/WHEEL
XStatic_JQuery.TableSorter-2.14.5.2.dist-info/namespace_packages.txt
XStatic_JQuery.TableSorter-2.14.5.2.dist-info/top_level.txt
XStatic_JQuery.TableSorter-2.14.5.2.dist-info/RECORD
