Metadata-Version: 2.1
Name: XStatic-JQuery.TableSorter
Version: 2.14.5.2
Summary: JQuery.TableSorter 2.14.5 (XStatic packaging standard)
Home-page: https://github.com/Mottie/tablesorter
Maintainer: Radomir Dopieralski
Maintainer-email: openstack@sheep.art.pl
License: (same as JQuery.TableSorter)
Keywords: jquery_tablesorter xstatic
Platform: any
